Workbook

Sheet Inputs 
A1: field | B1: FY2024 | C1: FY2025 | D1: FY2026
A2: revenue | B2: 25446.63 | C2: 27145.4 | D2: 27711.69
A3: gross_profit | B3: 15854.25 | C3: 17382.66 | D3: 17259.6
A4: ebit | B4: 5773.03 | C4: 6864.83 | D4: 5271.86
A5: net_income | B5: 4121.55 | C5: 5272.52 | D5: 3879.23
A6: sga | B6: 2783.96 | C6: 2955.02 | D6: 3086.23
A7: depreciation | B7: 941.61 | C7: 995.45 | D7: 1083.62
A8: total_assets | B8: 32717.82 | C8: 37387.04 | D8: 42495.98
A9: current_assets | B9: 19441.41 | C9: 23288.52 | D9: 24147.03
A10: current_liabilities | B10: 5245.77 | C10: 5483.96 | D10: 7013.59
A11: retained_earnings | B11: 21438.78 | C11: 25644.28 | D11: 28216
A12: total_equity | B12: 26706.43 | C12: 31193.45 | D12: 34431.95
A13: total_liabilities | B13: 5915.49 | C13: 6097.79 | D13: 7975.74
... A18: operating_cash_flow | B18: 4133.91 | C18: 5004.98 | D18: 3940.02

Sheet Altman
A1: LABEL | B1: FORMULA | C1: WHY IT MATTERS?
A2: X1 Working capital / Total assets | B2: =('Inputs '!D9-'Inputs '!D10)/'Inputs '!D8 -> 0.4031779 | C2: How much short-term cushion does Cipla have?
A3: X2 Retained earnings / Total assets | B3: ='Inputs '!D11/'Inputs '!D8 -> 0.66396869 | C3: How much of its assets were funded by past profits?
A4: X3 EBIT / Total assets | B4: ='Inputs '!D4/'Inputs '!D8 -> 0.1240555 | C4: How profitably does it use its assets?
A5: X4 Equity / Total liabilities | B5: ='Inputs '!D12/'Inputs '!D13 -> 4.3170853 | C5: How big is the cushion before creditors lose money?
A6: Z″ score | B6: =6.56*B2+3.26*B3+6.72*B4+1.05*B5 -> 10.175977
A7: Zone | B7: =IF(B6>2.6,"Safe",IF(B6>=1.1,"Grey","Distress")) -> Safe

Sheet Piotroski
A1: TEST | B1: VALUE LABEL | C1: VALUE | D1: RESULT | E1: WHY IT MATTERS
A2: 1. ROA > 0 | B2: ROA FY2026 | C2: ='Inputs '!D5/'Inputs '!C8 -> 0.10375868 | D2: =IF('Inputs '!D5/'Inputs '!C8>0,1,0) -> 1 | E2: The company is profitable
A3: 2. Operating cash flow > 0 | B3: ROA FY2025 | C3: ='Inputs '!C5/'Inputs '!B8 -> 0.16115132 | D3: =IF('Inputs '!D18>0,1,0) -> 1 | E3: It generates real cash
A4: 3. ROA improved | B4: Current ratio FY2026 | C4: ='Inputs '!D9/'Inputs '!D10 -> 3.4428916 | D4: =IF('Inputs '!D5/'Inputs '!C8>'Inputs '!C5/'Inputs '!B8,1,0) -> 0 | E4: Profitability is getting better
A5: 4. Cash flow > Net income | B5: Current ratio FY2025 | C5: ='Inputs '!C9/'Inputs '!C10 -> 4.2466612 | D5: =IF('Inputs '!D18>'Inputs '!D5,1,0) -> 1 | E5: Profits are backed by cash (accrual check)
A6: 5. Leverage fell (or stayed at zero) | B6: Gross margin FY2026 | C6: ='Inputs '!D3/'Inputs '!D2 -> 0.62282741 | D6: =IF(OR('Inputs '!D16/AVERAGE('Inputs '!C8:D8)<'Inputs '!C16/AVERAGE('Inputs '!B8:C8),AND('Inputs '!C16=0,'Inputs '!D16=0)),1,0) -> 0 | E6: Less reliance on long-term debt
A7: 6. Current ratio improved | B7: Gross margin FY2025 | C7: ='Inputs '!C3/'Inputs '!C2 -> 0.6403538 | D7: =IF('Inputs '!D9/'Inputs '!D10>'Inputs '!C9/'Inputs '!C10,1,0) -> 0 | E7: Short-term liquidity is better
A8: 7. No new shares issued | B8: Asset turnover FY2026 | C8: ='Inputs '!D2/'Inputs '!C8 -> 0.74121113 | D8: =IF('Inputs '!D17<='Inputs '!C17*1.01,1,0) -> 1 | E8: Didn't need to raise equity
A9: 8. Gross margin improved | B9: Asset turnover FY2025 | C9: ='Inputs '!C2/'Inputs '!B8 -> 0.82968242 | D9: =IF('Inputs '!D3/'Inputs '!D2>'Inputs '!C3/'Inputs '!C2,1,0) -> 0 | E9: Pricing power or cost control
A10: 9. Asset turnover improved | B10: Leverage FY2026 | C10: ='Inputs '!D16/AVERAGE('Inputs '!C8:D8) -> 0.0029410506 | D10: =IF('Inputs '!D2/'Inputs '!C8>'Inputs '!C2/'Inputs '!B8,1,0) -> 0 | E10: Using assets more efficiently
A11: F-score | B11: Leverage FY2025 | C11: ='Inputs '!C16/AVERAGE('Inputs '!B8:C8) -> 0.00034177374 | D11: =SUM(D2:D10) -> 4

Sheet Beneish
A1: INDEX | B1: FORMULA | C1: Red flag when high because…
A2: DSRI | B2: =('Inputs '!D14/'Inputs '!D2)/('Inputs '!C14/'Inputs '!C2) -> 0.99978824 | C2: Sales booked but cash not collected
A3: GMI | B3: =('Inputs '!C3/'Inputs '!C2)/('Inputs '!D3/'Inputs '!D2) -> 1.02814 | C3: Worsening margins create pressure to manipulate
A4: AQI | B4: =(1-('Inputs '!D9+'Inputs '!D15)/'Inputs '!D8)/(1-('Inputs '!C9+'Inputs '!C15)/'Inputs '!C8) -> 1.2335796 | C4: Costs pushed into vague "other" assets
A5: SGI | B5: ='Inputs '!D2/'Inputs '!C2 -> 1.0208614 | C5: Fast growth creates pressure to keep growing
A6: DEPI | B6: =('Inputs '!C7/('Inputs '!C7+'Inputs '!C15))/('Inputs '!D7/('Inputs '!D7+'Inputs '!D15)) -> 1.081522 | C6: Slowing depreciation inflates profit
A7: SGAI | B7: =('Inputs '!D6/'Inputs '!D2)/('Inputs '!C6/'Inputs '!C2) -> 1.02306 | C7: Overheads rising faster than sales
A8: LVGI | B8: =(('Inputs '!D10+'Inputs '!D16)/'Inputs '!D8)/(('Inputs '!C10+'Inputs '!C16)/'Inputs '!C8) -> 1.1415248 | C8: Rising debt raises the incentive to manipulate
A9: TATA | B9: =('Inputs '!D5-'Inputs '!D18)/'Inputs '!D8 -> -0.0014304882 | C9: The strongest signal: profit not backed by cash
A10: M-score | B10: =-4.84+0.92*B2+0.528*B3+0.404*B4+0.892*B5+0.115*B6-0.172*B7-0.327*B8+4.679*B9 -> -2.3999255
A11: Verdict | B11: =IF(B10>-1.78,"Likely manipulator","Unlikely manipulator") -> Unlikely manipulator
